README.md
setup.cfg
setup.py
GeoFun/KMLBuilder.py
GeoFun/__init__.py
GeoFun.egg-info/PKG-INFO
GeoFun.egg-info/SOURCES.txt
GeoFun.egg-info/dependency_links.txt
GeoFun.egg-info/requires.txt
GeoFun.egg-info/top_level.txt