Metadata-Version: 2.1
Name: GeoFun
Version: 0.1
Summary: A package to process and work with geo-data
Home-page: https://github.com/rik-git/GeoFun
Author: Riccardo Mogavero
Author-email: riccardomogavero@gmail.com
License: GNU GPLv3
Download-URL: https://github.com/rik-git/GeoFun/archive/0.1.tar.gz
Keywords: kml,geolocated images,GIS,kml builder,GoogleEarth,embed images into kml
Platform: UNKNOWN
Classifier: Development Status :: 3 - Alpha
Classifier: Intended Audience :: Developers
Classifier: Topic :: Software Development :: Build Tools
Classifier: License :: OSI Approved :: GNU General Public License v3 (GPLv3)
Classifier: Programming Language :: Python :: 3
Classifier: Programming Language :: Python :: 3.4
Classifier: Programming Language :: Python :: 3.5
Classifier: Programming Language :: Python :: 3.6
Classifier: Programming Language :: Python :: 3.7
